idgenerator/__init__.py
idgenerator/src/__init__.py
idgenerator/src/idgenerator.py
idgenerator/src/utils.py
idgenerator/test/__init__.py
idgenerator/test/test_idgenerator.py
vidgenerator-0.0.2.dist-info/LICENSE
vidgenerator-0.0.2.dist-info/METADATA
vidgenerator-0.0.2.dist-info/WHEEL
vidgenerator-0.0.2.dist-info/top_level.txt
vidgenerator-0.0.2.dist-info/RECORD
